forecastos/__init__.py
forecastos/exposure.py
forecastos/feature.py
forecastos/forecast.py
forecastos/global_utils.py
forecastos/provider.py
forecastos/utils/feature_engineering_mixin.py
forecastos/utils/readable.py
forecastos/utils/saveable.py
forecastos-0.2.4.dist-info/METADATA
forecastos-0.2.4.dist-info/WHEEL
forecastos-0.2.4.dist-info/RECORD
