Metadata-Version: 2.1
Name: forecastos
Version: 0.2.4
Summary: Headless feature store, pre-engineered ML features, and tools for ML workflows. By quantitative investors at forecastos.com
Author: Charlie Reese
Author-email: charlie.reese@hey.com
Requires-Python: >=3.9,<4.0
Classifier: Programming Language :: Python :: 3
Classifier: Programming Language :: Python :: 3.9
Classifier: Programming Language :: Python :: 3.10
Classifier: Programming Language :: Python :: 3.11
Classifier: Programming Language :: Python :: 3.12
Requires-Dist: boto3 (>=1.34.78,<2.0.0)
Requires-Dist: fastparquet (>=2024.5.0,<2025.0.0)
Requires-Dist: numpy (>=1.24.3)
Requires-Dist: pandas (>=2.2.2,<3.0.0)
Requires-Dist: requests (>=2.31.0,<3.0.0)
Requires-Dist: scikit-learn (>=1.5.1,<2.0.0)
Requires-Dist: scipy (>=1.13.1,<2.0.0)
